siumaai/__init__.py
siumaai/features/__init__.py
siumaai/features/utils.py
siumaai/features/ner/__init__.py
siumaai/features/ner/bio.py
siumaai/features/ner/global_pointer.py
siumaai/features/ner/mrc.py
siumaai/features/ner/span.py
siumaai/layers/__init__.py
siumaai/layers/crf.py
siumaai/layers/fgm.py
siumaai/layers/linears.py
siumaai/layers/pgd.py
siumaai/losses/__init__.py
siumaai/losses/focal_loss.py
siumaai/losses/label_smoothing.py
siumaai/losses/multilabel_categorical_crossentropy.py
siumaai/metrics/__init__.py
siumaai/metrics/ner.py
siumaai/models/__init__.py
siumaai/models/ner/__init__.py
siumaai/models/ner/crf_for_ner.py
siumaai/models/ner/global_pointer_for_ner.py
siumaai/models/ner/mrc_for_ner.py
siumaai/models/ner/span_for_ner.py
siumaai/pl_models/__init__.py
siumaai/pl_models/ner.py
siumaai/pl_models/plugins/__init__.py
siumaai/pl_models/plugins/fgm.py
siumaai-0.0.2.dist-info/METADATA
siumaai-0.0.2.dist-info/WHEEL
siumaai-0.0.2.dist-info/top_level.txt
siumaai-0.0.2.dist-info/RECORD
