Metadata-Version: 2.1
Name: siumaai
Version: 0.0.2
Summary: a siumaai for nlp
Home-page: UNKNOWN
Author: Zonzely
Author-email: UNKNOWN
License: Apache License 2.0
Platform: UNKNOWN
Requires-Dist: torch
Requires-Dist: transformers
Requires-Dist: pytorch-lightning
